mcp_mineru/__init__.py
mcp_mineru/server.py
mcp_mineru-0.1.3.dist-info/licenses/LICENSE
mcp_mineru-0.1.3.dist-info/METADATA
mcp_mineru-0.1.3.dist-info/WHEEL
mcp_mineru-0.1.3.dist-info/entry_points.txt
mcp_mineru-0.1.3.dist-info/top_level.txt
mcp_mineru-0.1.3.dist-info/RECORD
