Metadata-Version: 2.4
Name: mcp-mineru
Version: 0.1.3
Summary: MCP server for MinerU - Parse PDFs and images (OCR) with MLX acceleration on Apple Silicon
Author-email: TINKPA <tinkpa@example.com>
License: Apache-2.0
Project-URL: Homepage, https://github.com/TINKPA/mcp-mineru
Project-URL: Repository, https://github.com/TINKPA/mcp-mineru
Project-URL: Issues, https://github.com/TINKPA/mcp-mineru/issues
Project-URL: Documentation, https://github.com/TINKPA/mcp-mineru#readme
Keywords: mcp,mineru,pdf,ocr,image,parsing,mlx,apple-silicon,claude,screenshot,document
Classifier: Development Status :: 3 - Alpha
Classifier: Intended Audience :: Developers
Classifier: License :: OSI Approved :: Apache Software License
Classifier: Programming Language :: Python :: 3
Classifier: Programming Language :: Python :: 3.10
Classifier: Programming Language :: Python :: 3.11
Classifier: Programming Language :: Python :: 3.12
Classifier: Programming Language :: Python :: 3.13
Classifier: Topic :: Software Development :: Libraries :: Python Modules
Classifier: Topic :: Text Processing :: General
Requires-Python: <3.14,>=3.10
License-File: LICENSE
Requires-Dist: mcp>=1.0.0
Requires-Dist: mineru[core]>=2.6.4
Requires-Dist: loguru
Provides-Extra: dev
Requires-Dist: pytest>=7.0.0; extra == "dev"
Requires-Dist: pytest-asyncio>=0.21.0; extra == "dev"
Requires-Dist: black; extra == "dev"
Requires-Dist: ruff; extra == "dev"
Dynamic: license-file
